extraction/DiskInfo.py
extraction/LoadsInfo.py
extraction/NetworkInfo.py
extraction/__init__.py
sys_info_extraction-0.1.1.dist-info/METADATA
sys_info_extraction-0.1.1.dist-info/WHEEL
sys_info_extraction-0.1.1.dist-info/top_level.txt
sys_info_extraction-0.1.1.dist-info/RECORD
