Metadata-Version: 2.1
Name: sys-info-extraction
Version: 0.1.1
Summary: system information extraction packages
Home-page: https://github.com/support-yl/sys-info-extraction/blob/main/README.md
Author: mrl
Author-email: insupport@163.com
Requires-Dist: psutil
Requires-Dist: pyyaml
